{
  "date" : "Mon, 02 Jun, 2025 05:59:37 +0000",
  "doco" : "For each file: start is seconds after start activity occurred. Length = milliseconds activity took",
  "files" : [
    {
      "name" : "/fsh-generated/resources/ImplementationGuide-hl7.fhir.us.healthedata1-r6-sandbox.json",
      "size" : 7352,
      "processes" : [
        {
          "activity" : "load",
          "start" : 16,
          "length" : 12
        },
        {
          "activity" : "checkR4R4B",
          "start" : 20,
          "length" : 3
        },
        {
          "activity" : "generateNarratives",
          "start" : 20,
          "length" : 80
        },
        {
          "activity" : "validate",
          "start" : 22,
          "length" : 2406
        },
        {
          "activity" : "checkConformanceResources3",
          "start" : 27,
          "length" : 1
        },
        {
          "activity" : "generate1",
          "start" : 30,
          "length" : 47
        },
        {
          "activity" : "generate2",
          "start" : 32,
          "length" : 45
        },
        {
          "activity" : "generateValidationPack",
          "start" : 44,
          "length" : 1
        }
      ]
    },
    {
      "name" : "input/resources/StructureDefinition-us-core-patient.json",
      "size" : 16967,
      "processes" : [
        {
          "activity" : "loadResources",
          "start" : 16,
          "length" : 17
        },
        {
          "activity" : "load",
          "start" : 16,
          "length" : 25
        },
        {
          "activity" : "generateSnapshots",
          "start" : 16,
          "length" : 398
        },
        {
          "activity" : "load-configure",
          "start" : 20,
          "length" : 1
        },
        {
          "activity" : "loadDepInfo",
          "start" : 20,
          "length" : 1
        },
        {
          "activity" : "generateNarratives",
          "start" : 20,
          "length" : 293
        },
        {
          "activity" : "validate",
          "start" : 21,
          "length" : 1245
        },
        {
          "activity" : "checkConformanceResources2",
          "start" : 24,
          "length" : 2879
        },
        {
          "activity" : "scanForUsageStats",
          "start" : 27,
          "length" : 3
        },
        {
          "activity" : "generate1",
          "start" : 30,
          "length" : 291
        },
        {
          "activity" : "generate2",
          "start" : 32,
          "length" : 4347
        },
        {
          "activity" : "generate2",
          "start" : 37,
          "length" : 2146
        },
        {
          "activity" : "generateValidationPack",
          "start" : 44,
          "length" : 15
        },
        {
          "activity" : "scanExamplesForR5",
          "start" : 47,
          "length" : 1
        }
      ]
    },
    {
      "name" : "input/factories/Patient-1.json",
      "size" : 5734,
      "processes" : [
        {
          "activity" : "loadResources",
          "start" : 20,
          "length" : 5
        },
        {
          "activity" : "generateNarratives",
          "start" : 20,
          "length" : 379
        },
        {
          "activity" : "validate",
          "start" : 27,
          "length" : 602
        },
        {
          "activity" : "generate1",
          "start" : 31,
          "length" : 19
        },
        {
          "activity" : "generate2",
          "start" : 37,
          "length" : 29
        },
        {
          "activity" : "scanExamplesForR5",
          "start" : 47,
          "length" : 1
        }
      ]
    },
    {
      "name" : "input/factories/Patient-2.json",
      "size" : 4088,
      "processes" : [
        {
          "activity" : "loadResources",
          "start" : 20,
          "length" : 4
        },
        {
          "activity" : "checkR4R4B",
          "start" : 20,
          "length" : 1
        },
        {
          "activity" : "generateNarratives",
          "start" : 21,
          "length" : 15
        },
        {
          "activity" : "validate",
          "start" : 28,
          "length" : 1160
        },
        {
          "activity" : "generate1",
          "start" : 31,
          "length" : 14
        },
        {
          "activity" : "generate2",
          "start" : 37,
          "length" : 17
        }
      ]
    },
    {
      "name" : "input/factories/Patient-3.json",
      "size" : 4216,
      "processes" : [
        {
          "activity" : "loadResources",
          "start" : 20,
          "length" : 3
        },
        {
          "activity" : "generateNarratives",
          "start" : 21,
          "length" : 17
        },
        {
          "activity" : "validate",
          "start" : 29,
          "length" : 596
        },
        {
          "activity" : "generate1",
          "start" : 31,
          "length" : 12
        },
        {
          "activity" : "generate2",
          "start" : 37,
          "length" : 15
        }
      ]
    },
    {
      "name" : "input/factories/Patient-4.json",
      "size" : 4257,
      "processes" : [
        {
          "activity" : "loadResources",
          "start" : 20,
          "length" : 4
        },
        {
          "activity" : "checkR4R4B",
          "start" : 20,
          "length" : 1
        },
        {
          "activity" : "generateNarratives",
          "start" : 21,
          "length" : 10
        },
        {
          "activity" : "validate",
          "start" : 30,
          "length" : 620
        },
        {
          "activity" : "generate1",
          "start" : 31,
          "length" : 12
        },
        {
          "activity" : "generate2",
          "start" : 37,
          "length" : 20
        }
      ]
    }
  ]
}
